{"chunk_definitions":[{"row":28,"row_count":1,"visible":true,"expansion_state":0,"options":{"engine":"r","label":"unnamed-chunk-1646"},"document_id":"B2F82A87","chunk_id":"c90bsbd3pulwh","chunk_label":"unnamed-chunk-1"},{"row":73,"row_count":1,"visible":true,"expansion_state":0,"options":{"engine":"r","label":"unnamed-chunk-1649"},"document_id":"B2F82A87","chunk_id":"ccxruu2n7q5ry","chunk_label":"unnamed-chunk-3"},{"row":157,"row_count":1,"visible":true,"expansion_state":0,"options":{"engine":"r","label":"unnamed-chunk-1650"},"document_id":"B2F82A87","chunk_id":"cys733isctxa1","chunk_label":"unnamed-chunk-4"},{"row":239,"row_count":1,"visible":true,"expansion_state":0,"options":{"engine":"r","label":"unnamed-chunk-1651"},"document_id":"B2F82A87","chunk_id":"cczvd84lib0gv","chunk_label":"unnamed-chunk-5"},{"row":256,"row_count":1,"visible":true,"expansion_state":0,"options":{"engine":"r","label":"unnamed-chunk-1652"},"document_id":"B2F82A87","chunk_id":"cidqi5jqy66yq","chunk_label":"unnamed-chunk-6"},{"row":332,"row_count":1,"visible":true,"expansion_state":0,"options":{"engine":"r","label":"unnamed-chunk-1664"},"document_id":"B2F82A87","chunk_id":"cu9qzzwjf67r5","chunk_label":"unnamed-chunk-7"},{"row":472,"row_count":1,"visible":true,"expansion_state":0,"options":{"engine":"r","label":"unnamed-chunk-2036"},"document_id":"B2F82A87","chunk_id":"cjy31tg1toee8","chunk_label":"unnamed-chunk-9"},{"row":485,"row_count":1,"visible":true,"expansion_state":0,"options":{"engine":"r","label":"unnamed-chunk-1891"},"document_id":"B2F82A87","chunk_id":"ccfbdiy5oyk45","chunk_label":"unnamed-chunk-10"},{"row":576,"row_count":1,"visible":true,"expansion_state":0,"options":{"engine":"r","label":"unnamed-chunk-1991"},"document_id":"B2F82A87","chunk_id":"cu95u2sv5o1k4","chunk_label":"unnamed-chunk-11"},{"row":666,"row_count":1,"visible":true,"expansion_state":0,"options":{"engine":"r","label":"unnamed-chunk-1893"},"document_id":"B2F82A87","chunk_id":"ck2qtkbckdfu2","chunk_label":"unnamed-chunk-12"},{"row":682,"row_count":1,"visible":true,"expansion_state":0,"options":{"engine":"r","label":"unnamed-chunk-1894"},"document_id":"B2F82A87","chunk_id":"cilhsw8rz3eh4","chunk_label":"unnamed-chunk-13"},{"row":758,"row_count":1,"visible":true,"expansion_state":0,"options":{"engine":"r","label":"unnamed-chunk-1993"},"document_id":"B2F82A87","chunk_id":"cel32q8p3vwhs","chunk_label":"unnamed-chunk-14"},{"row":779,"row_count":1,"visible":true,"expansion_state":0,"options":{"engine":"r","label":"unnamed-chunk-2000"},"document_id":"B2F82A87","chunk_id":"cx5b26hhstunb","chunk_label":"unnamed-chunk-15"},{"row":797,"row_count":1,"visible":true,"expansion_state":0,"options":{"engine":"r","label":"unnamed-chunk-1980"},"document_id":"B2F82A87","chunk_id":"cg6jm74vwm9fj","chunk_label":"unnamed-chunk-16"},{"row":859,"row_count":1,"visible":true,"expansion_state":0,"options":{"engine":"r","label":"unnamed-chunk-1975"},"document_id":"B2F82A87","chunk_id":"c6ruf3tfs04eo","chunk_label":"unnamed-chunk-19"},{"row":923,"row_count":1,"visible":true,"expansion_state":0,"options":{"engine":"r","label":"unnamed-chunk-1923"},"document_id":"B2F82A87","chunk_id":"ccbijxr3x2uvy","chunk_label":"unnamed-chunk-20"},{"row":955,"row_count":1,"visible":true,"expansion_state":0,"options":{"engine":"r","label":"unnamed-chunk-1930"},"document_id":"B2F82A87","chunk_id":"ctslofs127g5a","chunk_label":"unnamed-chunk-21"},{"row":986,"row_count":1,"visible":true,"expansion_state":0,"options":{"engine":"r","label":"unnamed-chunk-2010"},"document_id":"B2F82A87","chunk_id":"cvtowwtqxaz51","chunk_label":"unnamed-chunk-22"},{"row":1014,"row_count":1,"visible":true,"expansion_state":0,"options":{"engine":"r","label":"unnamed-chunk-2012"},"document_id":"B2F82A87","chunk_id":"c6habt88fcjec","chunk_label":"unnamed-chunk-23"},{"row":1035,"row_count":1,"visible":true,"expansion_state":0,"options":{"engine":"r","label":"unnamed-chunk-1955"},"document_id":"B2F82A87","chunk_id":"c1zq8v1mxvqd5","chunk_label":"unnamed-chunk-24"},{"row":1062,"row_count":1,"visible":true,"expansion_state":0,"options":{"engine":"r","label":"unnamed-chunk-1956"},"document_id":"B2F82A87","chunk_id":"cuaicpwpmd5k1","chunk_label":"unnamed-chunk-25"},{"row":1184,"row_count":1,"visible":true,"expansion_state":0,"options":{"engine":"r","label":"unnamed-chunk-2155"},"document_id":"B2F82A87","chunk_id":"caxtfs9asr8ra","chunk_label":"unnamed-chunk-27"},{"row":1452,"row_count":1,"visible":true,"expansion_state":0,"options":{"engine":"r","label":"unnamed-chunk-2165"},"document_id":"B2F82A87","chunk_id":"c7z1mav7x0a8u","chunk_label":"unnamed-chunk-31"},{"row":1635,"row_count":1,"visible":true,"expansion_state":0,"options":{"engine":"r","label":"unnamed-chunk-2219"},"document_id":"B2F82A87","chunk_id":"cy1wfbh7hzue6","chunk_label":"unnamed-chunk-34"},{"row":1699,"row_count":1,"visible":true,"expansion_state":0,"options":{"engine":"r","label":"unnamed-chunk-2300"},"document_id":"B2F82A87","chunk_id":"cq3pvmoy0xs01","chunk_label":"unnamed-chunk-35"},{"row":1843,"row_count":1,"visible":true,"expansion_state":0,"options":{"engine":"r","label":"unnamed-chunk-2321"},"document_id":"B2F82A87","chunk_id":"cm0xi74yem163","chunk_label":"unnamed-chunk-36"},{"row":1961,"row_count":1,"visible":true,"expansion_state":0,"options":{"engine":"r","label":"unnamed-chunk-2333"},"document_id":"B2F82A87","chunk_id":"cr7hxyp4tbocd","chunk_label":"unnamed-chunk-37"},{"row":2098,"row_count":1,"visible":true,"expansion_state":0,"options":{"engine":"r","label":"unnamed-chunk-2348"},"document_id":"B2F82A87","chunk_id":"c6nyg1gzj2naz","chunk_label":"unnamed-chunk-38"}],"doc_write_time":1730124812,"chunk_rendered_width":700}